{
    "instaloader": {
        "node_type": "Post",
        "version": "4.13.1"
    },
    "node": {
        "__typename": "GraphImage",
        "accessibility_caption": null,
        "caption": ".\n\u590f\u4f11\u307f\u8a18\u5ff5\u305d\u306e34\u266a\n\n\u58f0\u512a\u30a2\u30cb\u30e1\u30c7\u30a3\u30a2\u9023\u8f09\u64ae\u5f71\u306e\u6642\u306e\u5199\u771f\u3067\u3059\u266a\n\u9ea6\u308f\u3089\u306e\u79c1\uff01\uff08\u7b11\uff09",
        "comments": 40,
        "date": 1566451564,
        "display_url": "https://instagram.fmnl4-6.fna.fbcdn.net/v/t51.2885-15/67178964_1663507127127451_3009067635413477386_n.jpg?stp=dst-jpg_e35&efg=eyJ2ZW5jb2RlX3RhZyI6ImltYWdlX3VybGdlbi4xMzUweDE1MDUuc2RyLmYyODg1LmRlZmF1bHRfaW1hZ2UifQ&_nc_ht=instagram.fmnl4-6.fna.fbcdn.net&_nc_cat=107&_nc_ohc=LjlQ2g6mb58Q7kNvgF2VFEw&edm=AEhyXUkBAAAA&ccb=7-5&ig_cache_key=MjExNTg3MTUzNTE0MjIwNzM4Nw%3D%3D.3-ccb7-5&oh=00_AYA2GOP-6-5QDGth28OzGduJRDRVaP10eeDYfeilQKKPOg&oe=66FB60C0&_nc_sid=8f1549",
        "edge_media_preview_like": {
            "count": 3628
        },
        "id": "2115871535142207387",
        "iphone_struct": {
            "__typename": "XDTMediaDict",
            "accessibility_caption": null,
            "ad_id": null,
            "affiliate_info": null,
            "all_previous_submitters": null,
            "audience": null,
            "boost_unavailable_identifier": null,
            "boost_unavailable_reason": null,
            "boosted_status": null,
            "can_reshare": null,
            "can_see_insights_as_brand": false,
            "can_viewer_reshare": false,
            "caption": {
                "created_at": 1566451565,
                "has_translation": null,
                "pk": "17850333049554436",
                "text": ".\n\u590f\u4f11\u307f\u8a18\u5ff5\u305d\u306e34\u266a\n\n\u58f0\u512a\u30a2\u30cb\u30e1\u30c7\u30a3\u30a2\u9023\u8f09\u64ae\u5f71\u306e\u6642\u306e\u5199\u771f\u3067\u3059\u266a\n\u9ea6\u308f\u3089\u306e\u79c1\uff01\uff08\u7b11\uff09"
            },
            "caption_is_edited": false,
            "carousel_media": null,
            "carousel_media_count": null,
            "carousel_parent_id": null,
            "clips_attribution_info": null,
            "clips_metadata": null,
            "coauthor_producers": [],
            "code": "B1dFfNqgv-b",
            "comment_count": 40,
            "commenting_disabled_for_viewer": null,
            "comments": null,
            "comments_disabled": null,
            "display_uri": "https://instagram.fmnl4-6.fna.fbcdn.net/v/t51.2885-15/67178964_1663507127127451_3009067635413477386_n.jpg?stp=c0.77.1350.1350a_dst-jpg_e35_s1080x1080&_nc_ht=instagram.fmnl4-6.fna.fbcdn.net&_nc_cat=107&_nc_ohc=LjlQ2g6mb58Q7kNvgF2VFEw&edm=AEhyXUkBAAAA&ccb=7-5&oh=00_AYDkzM0mc09XES4HHqulf6ajN3jQuZKru2LmJUlAUfaQow&oe=66FB60C0&_nc_sid=8f1549",
            "expiring_at": null,
            "explore": null,
            "facepile_top_likers": null,
            "feed_demotion_control": null,
            "feed_recs_demotion_control": null,
            "follow_hashtag_info": null,
            "group": null,
            "has_audio": null,
            "has_liked": false,
            "has_viewer_saved": null,
            "headline": null,
            "id": "2115871535142207387_2027519714",
            "ig_media_sharing_disabled": false,
            "image_versions2": {
                "candidates": [
                    {
                        "height": 1505,
                        "url": "https://instagram.fmnl4-6.fna.fbcdn.net/v/t51.2885-15/67178964_1663507127127451_3009067635413477386_n.jpg?stp=dst-jpg_e35&efg=eyJ2ZW5jb2RlX3RhZyI6ImltYWdlX3VybGdlbi4xMzUweDE1MDUuc2RyLmYyODg1LmRlZmF1bHRfaW1hZ2UifQ&_nc_ht=instagram.fmnl4-6.fna.fbcdn.net&_nc_cat=107&_nc_ohc=LjlQ2g6mb58Q7kNvgF2VFEw&edm=AEhyXUkBAAAA&ccb=7-5&ig_cache_key=MjExNTg3MTUzNTE0MjIwNzM4Nw%3D%3D.3-ccb7-5&oh=00_AYA2GOP-6-5QDGth28OzGduJRDRVaP10eeDYfeilQKKPOg&oe=66FB60C0&_nc_sid=8f1549",
                        "width": 1350
                    },
                    {
                        "height": 1204,
                        "url": "https://instagram.fmnl4-6.fna.fbcdn.net/v/t51.2885-15/67178964_1663507127127451_3009067635413477386_n.jpg?stp=dst-jpg_e35_p1080x1080&efg=eyJ2ZW5jb2RlX3RhZyI6ImltYWdlX3VybGdlbi4xMzUweDE1MDUuc2RyLmYyODg1LmRlZmF1bHRfaW1hZ2UifQ&_nc_ht=instagram.fmnl4-6.fna.fbcdn.net&_nc_cat=107&_nc_ohc=LjlQ2g6mb58Q7kNvgF2VFEw&_nc_gid=2ad11ccf84f24f06b1ffa7bad6059a83&edm=AEhyXUkBAAAA&ccb=7-5&ig_cache_key=MjExNTg3MTUzNTE0MjIwNzM4Nw%3D%3D.3-ccb7-5&oh=00_AYBw9ih1VLSj6m8XNqXbtW1WYc2ohe3lZR_g3V8MlQBxwA&oe=66FB60C0&_nc_sid=8f1549",
                        "width": 1080
                    },
                    {
                        "height": 803,
                        "url": "https://instagram.fmnl4-6.fna.fbcdn.net/v/t51.2885-15/67178964_1663507127127451_3009067635413477386_n.jpg?stp=dst-jpg_e35_p720x720&efg=eyJ2ZW5jb2RlX3RhZyI6ImltYWdlX3VybGdlbi4xMzUweDE1MDUuc2RyLmYyODg1LmRlZmF1bHRfaW1hZ2UifQ&_nc_ht=instagram.fmnl4-6.fna.fbcdn.net&_nc_cat=107&_nc_ohc=LjlQ2g6mb58Q7kNvgF2VFEw&edm=AEhyXUkBAAAA&ccb=7-5&ig_cache_key=MjExNTg3MTUzNTE0MjIwNzM4Nw%3D%3D.3-ccb7-5&oh=00_AYCp1kmROdQjRimlyUsyselC2oIBK-BLlhCJDv9FDX7qOA&oe=66FB60C0&_nc_sid=8f1549",
                        "width": 720
                    },
                    {
                        "height": 713,
                        "url": "https://instagram.fmnl4-6.fna.fbcdn.net/v/t51.2885-15/67178964_1663507127127451_3009067635413477386_n.jpg?stp=dst-jpg_e35_p640x640_sh0.08&efg=eyJ2ZW5jb2RlX3RhZyI6ImltYWdlX3VybGdlbi4xMzUweDE1MDUuc2RyLmYyODg1LmRlZmF1bHRfaW1hZ2UifQ&_nc_ht=instagram.fmnl4-6.fna.fbcdn.net&_nc_cat=107&_nc_ohc=LjlQ2g6mb58Q7kNvgF2VFEw&edm=AEhyXUkBAAAA&ccb=7-5&ig_cache_key=MjExNTg3MTUzNTE0MjIwNzM4Nw%3D%3D.3-ccb7-5&oh=00_AYAWh0zkjP9MMHIAHic22xABXuKiYf0EGfl6xwpymmE5mg&oe=66FB60C0&_nc_sid=8f1549",
                        "width": 640
                    },
                    {
                        "height": 535,
                        "url": "https://instagram.fmnl4-6.fna.fbcdn.net/v/t51.2885-15/67178964_1663507127127451_3009067635413477386_n.jpg?stp=dst-jpg_e35_p480x480&efg=eyJ2ZW5jb2RlX3RhZyI6ImltYWdlX3VybGdlbi4xMzUweDE1MDUuc2RyLmYyODg1LmRlZmF1bHRfaW1hZ2UifQ&_nc_ht=instagram.fmnl4-6.fna.fbcdn.net&_nc_cat=107&_nc_ohc=LjlQ2g6mb58Q7kNvgF2VFEw&_nc_gid=2ad11ccf84f24f06b1ffa7bad6059a83&edm=AEhyXUkBAAAA&ccb=7-5&ig_cache_key=MjExNTg3MTUzNTE0MjIwNzM4Nw%3D%3D.3-ccb7-5&oh=00_AYBL8drzYzFlNUtV0hKoFiBfwBPrbIwLp7sEIpzUm5Y8iA&oe=66FB60C0&_nc_sid=8f1549",
                        "width": 480
                    },
                    {
                        "height": 357,
                        "url": "https://instagram.fmnl4-6.fna.fbcdn.net/v/t51.2885-15/67178964_1663507127127451_3009067635413477386_n.jpg?stp=dst-jpg_e35_p320x320&efg=eyJ2ZW5jb2RlX3RhZyI6ImltYWdlX3VybGdlbi4xMzUweDE1MDUuc2RyLmYyODg1LmRlZmF1bHRfaW1hZ2UifQ&_nc_ht=instagram.fmnl4-6.fna.fbcdn.net&_nc_cat=107&_nc_ohc=LjlQ2g6mb58Q7kNvgF2VFEw&_nc_gid=2ad11ccf84f24f06b1ffa7bad6059a83&edm=AEhyXUkBAAAA&ccb=7-5&ig_cache_key=MjExNTg3MTUzNTE0MjIwNzM4Nw%3D%3D.3-ccb7-5&oh=00_AYBg7Sj6aQLklcMdXz3Y7K9gwOxCZsUA11QELzMN6j5iWA&oe=66FB60C0&_nc_sid=8f1549",
                        "width": 320
                    },
                    {
                        "height": 268,
                        "url": "https://instagram.fmnl4-6.fna.fbcdn.net/v/t51.2885-15/67178964_1663507127127451_3009067635413477386_n.jpg?stp=dst-jpg_e35_p240x240&efg=eyJ2ZW5jb2RlX3RhZyI6ImltYWdlX3VybGdlbi4xMzUweDE1MDUuc2RyLmYyODg1LmRlZmF1bHRfaW1hZ2UifQ&_nc_ht=instagram.fmnl4-6.fna.fbcdn.net&_nc_cat=107&_nc_ohc=LjlQ2g6mb58Q7kNvgF2VFEw&_nc_gid=2ad11ccf84f24f06b1ffa7bad6059a83&edm=AEhyXUkBAAAA&ccb=7-5&ig_cache_key=MjExNTg3MTUzNTE0MjIwNzM4Nw%3D%3D.3-ccb7-5&oh=00_AYCg-m20NmGXX1t1GZjWuTC30TOGvGr3a-kbKTYzNkvDEg&oe=66FB60C0&_nc_sid=8f1549",
                        "width": 240
                    },
                    {
                        "height": 1080,
                        "url": "https://instagram.fmnl4-6.fna.fbcdn.net/v/t51.2885-15/67178964_1663507127127451_3009067635413477386_n.jpg?stp=c0.77.1350.1350a_dst-jpg_e35_s1080x1080&efg=eyJ2ZW5jb2RlX3RhZyI6ImltYWdlX3VybGdlbi4xMzUweDE1MDUuc2RyLmYyODg1LmRlZmF1bHRfaW1hZ2UifQ&_nc_ht=instagram.fmnl4-6.fna.fbcdn.net&_nc_cat=107&_nc_ohc=LjlQ2g6mb58Q7kNvgF2VFEw&edm=AEhyXUkBAAAA&ccb=7-5&ig_cache_key=MjExNTg3MTUzNTE0MjIwNzM4Nw%3D%3D.3-ccb7-5&oh=00_AYDkzM0mc09XES4HHqulf6ajN3jQuZKru2LmJUlAUfaQow&oe=66FB60C0&_nc_sid=8f1549",
                        "width": 1080
                    },
                    {
                        "height": 750,
                        "url": "https://instagram.fmnl4-6.fna.fbcdn.net/v/t51.2885-15/67178964_1663507127127451_3009067635413477386_n.jpg?stp=c0.77.1350.1350a_dst-jpg_e35_s750x750_sh0.08&efg=eyJ2ZW5jb2RlX3RhZyI6ImltYWdlX3VybGdlbi4xMzUweDE1MDUuc2RyLmYyODg1LmRlZmF1bHRfaW1hZ2UifQ&_nc_ht=instagram.fmnl4-6.fna.fbcdn.net&_nc_cat=107&_nc_ohc=LjlQ2g6mb58Q7kNvgF2VFEw&_nc_gid=2ad11ccf84f24f06b1ffa7bad6059a83&edm=AEhyXUkBAAAA&ccb=7-5&ig_cache_key=MjExNTg3MTUzNTE0MjIwNzM4Nw%3D%3D.3-ccb7-5&oh=00_AYB9WrG37IhN5g2qFJ9VBEKef2gseUk7KseBp4pEFUZ6JQ&oe=66FB60C0&_nc_sid=8f1549",
                        "width": 750
                    },
                    {
                        "height": 640,
                        "url": "https://instagram.fmnl4-6.fna.fbcdn.net/v/t51.2885-15/67178964_1663507127127451_3009067635413477386_n.jpg?stp=c0.77.1350.1350a_dst-jpg_e35_s640x640_sh0.08&efg=eyJ2ZW5jb2RlX3RhZyI6ImltYWdlX3VybGdlbi4xMzUweDE1MDUuc2RyLmYyODg1LmRlZmF1bHRfaW1hZ2UifQ&_nc_ht=instagram.fmnl4-6.fna.fbcdn.net&_nc_cat=107&_nc_ohc=LjlQ2g6mb58Q7kNvgF2VFEw&edm=AEhyXUkBAAAA&ccb=7-5&ig_cache_key=MjExNTg3MTUzNTE0MjIwNzM4Nw%3D%3D.3-ccb7-5&oh=00_AYBCpG_uAOuprEqSxvAkE_3eYDYpxV2SjA_4wD2w_-ydhA&oe=66FB60C0&_nc_sid=8f1549",
                        "width": 640
                    },
                    {
                        "height": 480,
                        "url": "https://instagram.fmnl4-6.fna.fbcdn.net/v/t51.2885-15/67178964_1663507127127451_3009067635413477386_n.jpg?stp=c0.77.1350.1350a_dst-jpg_e35_s480x480&efg=eyJ2ZW5jb2RlX3RhZyI6ImltYWdlX3VybGdlbi4xMzUweDE1MDUuc2RyLmYyODg1LmRlZmF1bHRfaW1hZ2UifQ&_nc_ht=instagram.fmnl4-6.fna.fbcdn.net&_nc_cat=107&_nc_ohc=LjlQ2g6mb58Q7kNvgF2VFEw&edm=AEhyXUkBAAAA&ccb=7-5&ig_cache_key=MjExNTg3MTUzNTE0MjIwNzM4Nw%3D%3D.3-ccb7-5&oh=00_AYAEZVgXrItTrJ0ohzUjq9khx1TLZixZk6VgGpEZhSOHtw&oe=66FB60C0&_nc_sid=8f1549",
                        "width": 480
                    },
                    {
                        "height": 320,
                        "url": "https://instagram.fmnl4-6.fna.fbcdn.net/v/t51.2885-15/67178964_1663507127127451_3009067635413477386_n.jpg?stp=c0.77.1350.1350a_dst-jpg_e35_s320x320&efg=eyJ2ZW5jb2RlX3RhZyI6ImltYWdlX3VybGdlbi4xMzUweDE1MDUuc2RyLmYyODg1LmRlZmF1bHRfaW1hZ2UifQ&_nc_ht=instagram.fmnl4-6.fna.fbcdn.net&_nc_cat=107&_nc_ohc=LjlQ2g6mb58Q7kNvgF2VFEw&edm=AEhyXUkBAAAA&ccb=7-5&ig_cache_key=MjExNTg3MTUzNTE0MjIwNzM4Nw%3D%3D.3-ccb7-5&oh=00_AYCs_x5TChevMnOn-WQZIDlGmnY1RhfK717GLbdHtseSUg&oe=66FB60C0&_nc_sid=8f1549",
                        "width": 320
                    },
                    {
                        "height": 240,
                        "url": "https://instagram.fmnl4-6.fna.fbcdn.net/v/t51.2885-15/67178964_1663507127127451_3009067635413477386_n.jpg?stp=c0.77.1350.1350a_dst-jpg_e35_s240x240&efg=eyJ2ZW5jb2RlX3RhZyI6ImltYWdlX3VybGdlbi4xMzUweDE1MDUuc2RyLmYyODg1LmRlZmF1bHRfaW1hZ2UifQ&_nc_ht=instagram.fmnl4-6.fna.fbcdn.net&_nc_cat=107&_nc_ohc=LjlQ2g6mb58Q7kNvgF2VFEw&_nc_gid=2ad11ccf84f24f06b1ffa7bad6059a83&edm=AEhyXUkBAAAA&ccb=7-5&ig_cache_key=MjExNTg3MTUzNTE0MjIwNzM4Nw%3D%3D.3-ccb7-5&oh=00_AYAq1znchHEyJxwImn_k5Fnl6DTcv9sJlmKxCYN37nIynA&oe=66FB60C0&_nc_sid=8f1549",
                        "width": 240
                    },
                    {
                        "height": 150,
                        "url": "https://instagram.fmnl4-6.fna.fbcdn.net/v/t51.2885-15/67178964_1663507127127451_3009067635413477386_n.jpg?stp=c0.77.1350.1350a_dst-jpg_e35_s150x150&efg=eyJ2ZW5jb2RlX3RhZyI6ImltYWdlX3VybGdlbi4xMzUweDE1MDUuc2RyLmYyODg1LmRlZmF1bHRfaW1hZ2UifQ&_nc_ht=instagram.fmnl4-6.fna.fbcdn.net&_nc_cat=107&_nc_ohc=LjlQ2g6mb58Q7kNvgF2VFEw&_nc_gid=2ad11ccf84f24f06b1ffa7bad6059a83&edm=AEhyXUkBAAAA&ccb=7-5&ig_cache_key=MjExNTg3MTUzNTE0MjIwNzM4Nw%3D%3D.3-ccb7-5&oh=00_AYDLcu2p43olgRCqiSzFCH9WQmZ6aSHV9agmP9sMV731oQ&oe=66FB60C0&_nc_sid=8f1549",
                        "width": 150
                    }
                ]
            },
            "inventory_source": null,
            "invited_coauthor_producers": [],
            "is_dash_eligible": null,
            "is_paid_partnership": false,
            "is_seen": null,
            "like_and_view_counts_disabled": false,
            "like_count": 3628,
            "link": null,
            "location": null,
            "main_feed_carousel_starting_media_id": null,
            "media_cropping_info": null,
            "media_level_comment_controls": null,
            "media_overlay_info": null,
            "media_type": 1,
            "number_of_qualities": null,
            "open_carousel_submission_state": null,
            "organic_tracking_token": "eyJ2ZXJzaW9uIjo1LCJwYXlsb2FkIjp7ImlzX2FuYWx5dGljc190cmFja2VkIjp0cnVlLCJ1dWlkIjoiMmFkMTFjY2Y4NGYyNGYwNmIxZmZhN2JhZDYwNTlhODMyMTE1ODcxNTM1MTQyMjA3Mzg3In0sInNpZ25hdHVyZSI6IiJ9",
            "original_height": 1505,
            "original_width": 1350,
            "owner": {
                "__typename": "XDTUserDict",
                "friendship_status": null,
                "id": "2027519714",
                "is_embeds_disabled": null,
                "is_private": false,
                "is_unpublished": false,
                "is_verified": false,
                "pk": "2027519714",
                "profile_pic_url": "https://instagram.fmnl4-2.fna.fbcdn.net/v/t51.2885-19/11374159_753097248149705_168906061_a.jpg?stp=dst-jpg_s150x150&_nc_ht=instagram.fmnl4-2.fna.fbcdn.net&_nc_cat=105&_nc_ohc=3rj5kw39Jy8Q7kNvgE4yGuo&_nc_gid=2ad11ccf84f24f06b1ffa7bad6059a83&edm=AEhyXUkBAAAA&ccb=7-5&oh=00_AYBlOvdPJN2WAET4azUw8ABIUjLh0YVZ4VBaFkzSTuN6Wg&oe=66FB55A0&_nc_sid=8f1549",
                "show_account_transparency_details": true,
                "supervision_info": null,
                "transparency_label": null,
                "transparency_product": null,
                "transparency_product_enabled": false,
                "username": "yuihorie_official"
            },
            "photo_of_you": false,
            "pk": "2115871535142207387",
            "preview": null,
            "previous_submitter": null,
            "product_type": "feed",
            "saved_collection_ids": null,
            "share_urls": null,
            "sharing_friction_info": {
                "bloks_app_url": null,
                "should_have_sharing_friction": false
            },
            "social_context": null,
            "sponsor_tags": null,
            "story_cta": null,
            "taken_at": 1566451564,
            "thumbnails": null,
            "timeline_pinned_user_ids": null,
            "title": null,
            "top_likers": null,
            "upcoming_event": null,
            "user": {
                "__typename": "XDTUserDict",
                "friendship_status": null,
                "full_name": "\u5800\u6c5f\u7531\u8863",
                "hd_profile_pic_url_info": {
                    "url": "https://instagram.fmnl4-2.fna.fbcdn.net/v/t51.2885-19/11374159_753097248149705_168906061_a.jpg?_nc_ht=instagram.fmnl4-2.fna.fbcdn.net&_nc_cat=105&_nc_ohc=3rj5kw39Jy8Q7kNvgE4yGuo&_nc_gid=2ad11ccf84f24f06b1ffa7bad6059a83&edm=AEhyXUkBAAAA&ccb=7-5&oh=00_AYCv_n3kDuGXbkEAJKkw1InSqE7CUgmAPX3X98kLP4S6Sg&oe=66FB55A0&_nc_sid=8f1549"
                },
                "id": "2027519714",
                "is_embeds_disabled": null,
                "is_private": false,
                "is_unpublished": false,
                "is_verified": false,
                "latest_besties_reel_media": null,
                "latest_reel_media": null,
                "live_broadcast_id": null,
                "live_broadcast_visibility": null,
                "pk": "2027519714",
                "profile_pic_url": "https://instagram.fmnl4-2.fna.fbcdn.net/v/t51.2885-19/11374159_753097248149705_168906061_a.jpg?stp=dst-jpg_s150x150&_nc_ht=instagram.fmnl4-2.fna.fbcdn.net&_nc_cat=105&_nc_ohc=3rj5kw39Jy8Q7kNvgE4yGuo&_nc_gid=2ad11ccf84f24f06b1ffa7bad6059a83&edm=AEhyXUkBAAAA&ccb=7-5&oh=00_AYBlOvdPJN2WAET4azUw8ABIUjLh0YVZ4VBaFkzSTuN6Wg&oe=66FB55A0&_nc_sid=8f1549",
                "seen": null,
                "supervision_info": null,
                "username": "yuihorie_official"
            },
            "usertags": null,
            "video_dash_manifest": null,
            "video_versions": null,
            "view_count": null
        },
        "is_video": false,
        "owner": {
            "full_name": "\u5800\u6c5f\u7531\u8863",
            "id": "2027519714",
            "iphone_struct": {
                "__typename": "XDTUserDict",
                "friendship_status": null,
                "full_name": "\u5800\u6c5f\u7531\u8863",
                "hd_profile_pic_url_info": {
                    "url": "https://instagram.fmnl4-2.fna.fbcdn.net/v/t51.2885-19/11374159_753097248149705_168906061_a.jpg?_nc_ht=instagram.fmnl4-2.fna.fbcdn.net&_nc_cat=105&_nc_ohc=3rj5kw39Jy8Q7kNvgE4yGuo&_nc_gid=2ad11ccf84f24f06b1ffa7bad6059a83&edm=AEhyXUkBAAAA&ccb=7-5&oh=00_AYCv_n3kDuGXbkEAJKkw1InSqE7CUgmAPX3X98kLP4S6Sg&oe=66FB55A0&_nc_sid=8f1549"
                },
                "id": "2027519714",
                "is_embeds_disabled": null,
                "is_private": false,
                "is_unpublished": false,
                "is_verified": false,
                "latest_besties_reel_media": null,
                "latest_reel_media": null,
                "live_broadcast_id": null,
                "live_broadcast_visibility": null,
                "pk": "2027519714",
                "profile_pic_url": "https://instagram.fmnl4-2.fna.fbcdn.net/v/t51.2885-19/11374159_753097248149705_168906061_a.jpg?stp=dst-jpg_s150x150&_nc_ht=instagram.fmnl4-2.fna.fbcdn.net&_nc_cat=105&_nc_ohc=3rj5kw39Jy8Q7kNvgE4yGuo&_nc_gid=2ad11ccf84f24f06b1ffa7bad6059a83&edm=AEhyXUkBAAAA&ccb=7-5&oh=00_AYBlOvdPJN2WAET4azUw8ABIUjLh0YVZ4VBaFkzSTuN6Wg&oe=66FB55A0&_nc_sid=8f1549",
                "seen": null,
                "supervision_info": null,
                "username": "yuihorie_official"
            },
            "is_private": false,
            "profile_pic_url_hd": "https://instagram.fmnl4-2.fna.fbcdn.net/v/t51.2885-19/11374159_753097248149705_168906061_a.jpg?stp=dst-jpg_s150x150&_nc_ht=instagram.fmnl4-2.fna.fbcdn.net&_nc_cat=105&_nc_ohc=3rj5kw39Jy8Q7kNvgE4yGuo&_nc_gid=2ad11ccf84f24f06b1ffa7bad6059a83&edm=AEhyXUkBAAAA&ccb=7-5&oh=00_AYBlOvdPJN2WAET4azUw8ABIUjLh0YVZ4VBaFkzSTuN6Wg&oe=66FB55A0&_nc_sid=8f1549",
            "username": "yuihorie_official"
        },
        "shortcode": "B1dFfNqgv-b",
        "title": null,
        "viewer_has_liked": false
    }
}