{
    "instaloader": {
        "node_type": "Post",
        "version": "4.13.1"
    },
    "node": {
        "__typename": "GraphImage",
        "accessibility_caption": null,
        "caption": ".\n\u30cf\u30c3\u30d4\u30fc\u30cf\u30ed\u30a6\u30a3\u30f3\ud83c\udf83\n\n\u30a2\u30af\u30b9\u30bf\u3068100\u5747\u3067\u8cb7\u3063\u305f\u5c0f\u7269\u3067\u64ae\u5f71\u3057\u3066\u307f\u307e\u3057\u305f\u266a",
        "comments": 64,
        "date": 1667044410,
        "display_url": "https://instagram.fmnl4-7.fna.fbcdn.net/v/t51.29350-15/312985508_516547690048840_7681537962679898969_n.jpg?stp=dst-jpg_e35&efg=eyJ2ZW5jb2RlX3RhZyI6ImltYWdlX3VybGdlbi4xMjgweDEyODMuc2RyLmYyOTM1MC5kZWZhdWx0X2ltYWdlIn0&_nc_ht=instagram.fmnl4-7.fna.fbcdn.net&_nc_cat=104&_nc_ohc=ET194TXqk_YQ7kNvgEphgzG&_nc_gid=edf72fe289b045f2944e4f632c4d0cc0&edm=AEhyXUkBAAAA&ccb=7-5&ig_cache_key=Mjk1OTcwNTQ4NzEwNjkwNTgyNg%3D%3D.3-ccb7-5&oh=00_AYA4Y0M7klVtaGmL7OZIcnJYcOwL3fwXMkvuFdPg-5BMAg&oe=66FB644A&_nc_sid=8f1549",
        "edge_media_preview_like": {
            "count": 4355
        },
        "id": "2959705487106905826",
        "iphone_struct": {
            "__typename": "XDTMediaDict",
            "accessibility_caption": null,
            "ad_id": null,
            "affiliate_info": null,
            "all_previous_submitters": null,
            "audience": null,
            "boost_unavailable_identifier": null,
            "boost_unavailable_reason": null,
            "boosted_status": null,
            "can_reshare": null,
            "can_see_insights_as_brand": false,
            "can_viewer_reshare": false,
            "caption": {
                "created_at": 1667044411,
                "has_translation": null,
                "pk": "17986818817567416",
                "text": ".\n\u30cf\u30c3\u30d4\u30fc\u30cf\u30ed\u30a6\u30a3\u30f3\ud83c\udf83\n\n\u30a2\u30af\u30b9\u30bf\u3068100\u5747\u3067\u8cb7\u3063\u305f\u5c0f\u7269\u3067\u64ae\u5f71\u3057\u3066\u307f\u307e\u3057\u305f\u266a"
            },
            "caption_is_edited": false,
            "carousel_media": null,
            "carousel_media_count": null,
            "carousel_parent_id": null,
            "clips_attribution_info": null,
            "clips_metadata": null,
            "coauthor_producers": [],
            "code": "CkS_HWWyBbi",
            "comment_count": 64,
            "commenting_disabled_for_viewer": null,
            "comments": null,
            "comments_disabled": null,
            "display_uri": "https://instagram.fmnl4-7.fna.fbcdn.net/v/t51.29350-15/312985508_516547690048840_7681537962679898969_n.jpg?stp=c0.1.1280.1280a_dst-jpg_e35_s1080x1080&_nc_ht=instagram.fmnl4-7.fna.fbcdn.net&_nc_cat=104&_nc_ohc=ET194TXqk_YQ7kNvgEphgzG&edm=AEhyXUkBAAAA&ccb=7-5&oh=00_AYD1FQSvpguRGZjGAwD7yZKXdh4rjiwUnomR50GFPc9C5w&oe=66FB644A&_nc_sid=8f1549",
            "expiring_at": null,
            "explore": null,
            "facepile_top_likers": null,
            "feed_demotion_control": null,
            "feed_recs_demotion_control": null,
            "follow_hashtag_info": null,
            "group": null,
            "has_audio": null,
            "has_liked": false,
            "has_viewer_saved": null,
            "headline": null,
            "id": "2959705487106905826_2027519714",
            "ig_media_sharing_disabled": false,
            "image_versions2": {
                "candidates": [
                    {
                        "height": 1283,
                        "url": "https://instagram.fmnl4-7.fna.fbcdn.net/v/t51.29350-15/312985508_516547690048840_7681537962679898969_n.jpg?stp=dst-jpg_e35&efg=eyJ2ZW5jb2RlX3RhZyI6ImltYWdlX3VybGdlbi4xMjgweDEyODMuc2RyLmYyOTM1MC5kZWZhdWx0X2ltYWdlIn0&_nc_ht=instagram.fmnl4-7.fna.fbcdn.net&_nc_cat=104&_nc_ohc=ET194TXqk_YQ7kNvgEphgzG&_nc_gid=edf72fe289b045f2944e4f632c4d0cc0&edm=AEhyXUkBAAAA&ccb=7-5&ig_cache_key=Mjk1OTcwNTQ4NzEwNjkwNTgyNg%3D%3D.3-ccb7-5&oh=00_AYA4Y0M7klVtaGmL7OZIcnJYcOwL3fwXMkvuFdPg-5BMAg&oe=66FB644A&_nc_sid=8f1549",
                        "width": 1280
                    },
                    {
                        "height": 1083,
                        "url": "https://instagram.fmnl4-7.fna.fbcdn.net/v/t51.29350-15/312985508_516547690048840_7681537962679898969_n.jpg?stp=dst-jpg_e35_p1080x1080&efg=eyJ2ZW5jb2RlX3RhZyI6ImltYWdlX3VybGdlbi4xMjgweDEyODMuc2RyLmYyOTM1MC5kZWZhdWx0X2ltYWdlIn0&_nc_ht=instagram.fmnl4-7.fna.fbcdn.net&_nc_cat=104&_nc_ohc=ET194TXqk_YQ7kNvgEphgzG&_nc_gid=edf72fe289b045f2944e4f632c4d0cc0&edm=AEhyXUkBAAAA&ccb=7-5&ig_cache_key=Mjk1OTcwNTQ4NzEwNjkwNTgyNg%3D%3D.3-ccb7-5&oh=00_AYB8hdhhV7RQNCn6IpZ1kw7csgXeVRj1kebuo-WYsCGbig&oe=66FB644A&_nc_sid=8f1549",
                        "width": 1080
                    },
                    {
                        "height": 722,
                        "url": "https://instagram.fmnl4-7.fna.fbcdn.net/v/t51.29350-15/312985508_516547690048840_7681537962679898969_n.jpg?stp=dst-jpg_e35_p720x720&efg=eyJ2ZW5jb2RlX3RhZyI6ImltYWdlX3VybGdlbi4xMjgweDEyODMuc2RyLmYyOTM1MC5kZWZhdWx0X2ltYWdlIn0&_nc_ht=instagram.fmnl4-7.fna.fbcdn.net&_nc_cat=104&_nc_ohc=ET194TXqk_YQ7kNvgEphgzG&edm=AEhyXUkBAAAA&ccb=7-5&ig_cache_key=Mjk1OTcwNTQ4NzEwNjkwNTgyNg%3D%3D.3-ccb7-5&oh=00_AYCzIsNaKx2xP4Io-4gavIRz46vwfkePPwrAFUtTPfpumw&oe=66FB644A&_nc_sid=8f1549",
                        "width": 720
                    },
                    {
                        "height": 642,
                        "url": "https://instagram.fmnl4-7.fna.fbcdn.net/v/t51.29350-15/312985508_516547690048840_7681537962679898969_n.jpg?stp=dst-jpg_e35_p640x640_sh0.08&efg=eyJ2ZW5jb2RlX3RhZyI6ImltYWdlX3VybGdlbi4xMjgweDEyODMuc2RyLmYyOTM1MC5kZWZhdWx0X2ltYWdlIn0&_nc_ht=instagram.fmnl4-7.fna.fbcdn.net&_nc_cat=104&_nc_ohc=ET194TXqk_YQ7kNvgEphgzG&_nc_gid=edf72fe289b045f2944e4f632c4d0cc0&edm=AEhyXUkBAAAA&ccb=7-5&ig_cache_key=Mjk1OTcwNTQ4NzEwNjkwNTgyNg%3D%3D.3-ccb7-5&oh=00_AYAyUyU7x8_7JFGXXTKJRWlJQGVxMQGU4jWI91CyK6VPxw&oe=66FB644A&_nc_sid=8f1549",
                        "width": 640
                    },
                    {
                        "height": 481,
                        "url": "https://instagram.fmnl4-7.fna.fbcdn.net/v/t51.29350-15/312985508_516547690048840_7681537962679898969_n.jpg?stp=dst-jpg_e35_p480x480&efg=eyJ2ZW5jb2RlX3RhZyI6ImltYWdlX3VybGdlbi4xMjgweDEyODMuc2RyLmYyOTM1MC5kZWZhdWx0X2ltYWdlIn0&_nc_ht=instagram.fmnl4-7.fna.fbcdn.net&_nc_cat=104&_nc_ohc=ET194TXqk_YQ7kNvgEphgzG&edm=AEhyXUkBAAAA&ccb=7-5&ig_cache_key=Mjk1OTcwNTQ4NzEwNjkwNTgyNg%3D%3D.3-ccb7-5&oh=00_AYCEa5ZjKEReuqzYqockHfdqmKXPbZtDOMlAzpZ7yOqfYg&oe=66FB644A&_nc_sid=8f1549",
                        "width": 480
                    },
                    {
                        "height": 321,
                        "url": "https://instagram.fmnl4-7.fna.fbcdn.net/v/t51.29350-15/312985508_516547690048840_7681537962679898969_n.jpg?stp=dst-jpg_e35_p320x320&efg=eyJ2ZW5jb2RlX3RhZyI6ImltYWdlX3VybGdlbi4xMjgweDEyODMuc2RyLmYyOTM1MC5kZWZhdWx0X2ltYWdlIn0&_nc_ht=instagram.fmnl4-7.fna.fbcdn.net&_nc_cat=104&_nc_ohc=ET194TXqk_YQ7kNvgEphgzG&_nc_gid=edf72fe289b045f2944e4f632c4d0cc0&edm=AEhyXUkBAAAA&ccb=7-5&ig_cache_key=Mjk1OTcwNTQ4NzEwNjkwNTgyNg%3D%3D.3-ccb7-5&oh=00_AYCmOVhDjVWMfWk7ODotZfXYMwMgSqhQ6BbT6Y65eRhDeg&oe=66FB644A&_nc_sid=8f1549",
                        "width": 320
                    },
                    {
                        "height": 241,
                        "url": "https://instagram.fmnl4-7.fna.fbcdn.net/v/t51.29350-15/312985508_516547690048840_7681537962679898969_n.jpg?stp=dst-jpg_e35_p240x240&efg=eyJ2ZW5jb2RlX3RhZyI6ImltYWdlX3VybGdlbi4xMjgweDEyODMuc2RyLmYyOTM1MC5kZWZhdWx0X2ltYWdlIn0&_nc_ht=instagram.fmnl4-7.fna.fbcdn.net&_nc_cat=104&_nc_ohc=ET194TXqk_YQ7kNvgEphgzG&_nc_gid=edf72fe289b045f2944e4f632c4d0cc0&edm=AEhyXUkBAAAA&ccb=7-5&ig_cache_key=Mjk1OTcwNTQ4NzEwNjkwNTgyNg%3D%3D.3-ccb7-5&oh=00_AYBKWsVM6zFmNASygxtr5_27NDFMPmd4m4yyEp4qtearPA&oe=66FB644A&_nc_sid=8f1549",
                        "width": 240
                    },
                    {
                        "height": 1080,
                        "url": "https://instagram.fmnl4-7.fna.fbcdn.net/v/t51.29350-15/312985508_516547690048840_7681537962679898969_n.jpg?stp=c0.1.1280.1280a_dst-jpg_e35_s1080x1080&efg=eyJ2ZW5jb2RlX3RhZyI6ImltYWdlX3VybGdlbi4xMjgweDEyODMuc2RyLmYyOTM1MC5kZWZhdWx0X2ltYWdlIn0&_nc_ht=instagram.fmnl4-7.fna.fbcdn.net&_nc_cat=104&_nc_ohc=ET194TXqk_YQ7kNvgEphgzG&_nc_gid=edf72fe289b045f2944e4f632c4d0cc0&edm=AEhyXUkBAAAA&ccb=7-5&ig_cache_key=Mjk1OTcwNTQ4NzEwNjkwNTgyNg%3D%3D.3-ccb7-5&oh=00_AYB8l9VyzgH6WRna7pnrRfa5r3BxO4BO4b39do6RhoFEzg&oe=66FB644A&_nc_sid=8f1549",
                        "width": 1080
                    },
                    {
                        "height": 750,
                        "url": "https://instagram.fmnl4-7.fna.fbcdn.net/v/t51.29350-15/312985508_516547690048840_7681537962679898969_n.jpg?stp=c0.1.1280.1280a_dst-jpg_e35_s750x750_sh0.08&efg=eyJ2ZW5jb2RlX3RhZyI6ImltYWdlX3VybGdlbi4xMjgweDEyODMuc2RyLmYyOTM1MC5kZWZhdWx0X2ltYWdlIn0&_nc_ht=instagram.fmnl4-7.fna.fbcdn.net&_nc_cat=104&_nc_ohc=ET194TXqk_YQ7kNvgEphgzG&_nc_gid=edf72fe289b045f2944e4f632c4d0cc0&edm=AEhyXUkBAAAA&ccb=7-5&ig_cache_key=Mjk1OTcwNTQ4NzEwNjkwNTgyNg%3D%3D.3-ccb7-5&oh=00_AYBLm-0jEm3tis4elnpCEfyf79GvosYV9AqtI7bozzJKfw&oe=66FB644A&_nc_sid=8f1549",
                        "width": 750
                    },
                    {
                        "height": 640,
                        "url": "https://instagram.fmnl4-7.fna.fbcdn.net/v/t51.29350-15/312985508_516547690048840_7681537962679898969_n.jpg?stp=c0.1.1280.1280a_dst-jpg_e35_s640x640_sh0.08&efg=eyJ2ZW5jb2RlX3RhZyI6ImltYWdlX3VybGdlbi4xMjgweDEyODMuc2RyLmYyOTM1MC5kZWZhdWx0X2ltYWdlIn0&_nc_ht=instagram.fmnl4-7.fna.fbcdn.net&_nc_cat=104&_nc_ohc=ET194TXqk_YQ7kNvgEphgzG&edm=AEhyXUkBAAAA&ccb=7-5&ig_cache_key=Mjk1OTcwNTQ4NzEwNjkwNTgyNg%3D%3D.3-ccb7-5&oh=00_AYBE_vXvaWIxYwP4kW6aDrIx0cKY-iUUrOSM4GycJj5Prg&oe=66FB644A&_nc_sid=8f1549",
                        "width": 640
                    },
                    {
                        "height": 480,
                        "url": "https://instagram.fmnl4-7.fna.fbcdn.net/v/t51.29350-15/312985508_516547690048840_7681537962679898969_n.jpg?stp=c0.1.1280.1280a_dst-jpg_e35_s480x480&efg=eyJ2ZW5jb2RlX3RhZyI6ImltYWdlX3VybGdlbi4xMjgweDEyODMuc2RyLmYyOTM1MC5kZWZhdWx0X2ltYWdlIn0&_nc_ht=instagram.fmnl4-7.fna.fbcdn.net&_nc_cat=104&_nc_ohc=ET194TXqk_YQ7kNvgEphgzG&_nc_gid=edf72fe289b045f2944e4f632c4d0cc0&edm=AEhyXUkBAAAA&ccb=7-5&ig_cache_key=Mjk1OTcwNTQ4NzEwNjkwNTgyNg%3D%3D.3-ccb7-5&oh=00_AYD0IdGGocgs0KjN8Fhf6p_fR0Aqp9i0N3F79YrXjldyAA&oe=66FB644A&_nc_sid=8f1549",
                        "width": 480
                    },
                    {
                        "height": 320,
                        "url": "https://instagram.fmnl4-7.fna.fbcdn.net/v/t51.29350-15/312985508_516547690048840_7681537962679898969_n.jpg?stp=c0.1.1280.1280a_dst-jpg_e35_s320x320&efg=eyJ2ZW5jb2RlX3RhZyI6ImltYWdlX3VybGdlbi4xMjgweDEyODMuc2RyLmYyOTM1MC5kZWZhdWx0X2ltYWdlIn0&_nc_ht=instagram.fmnl4-7.fna.fbcdn.net&_nc_cat=104&_nc_ohc=ET194TXqk_YQ7kNvgEphgzG&_nc_gid=edf72fe289b045f2944e4f632c4d0cc0&edm=AEhyXUkBAAAA&ccb=7-5&ig_cache_key=Mjk1OTcwNTQ4NzEwNjkwNTgyNg%3D%3D.3-ccb7-5&oh=00_AYCYGGt3eg6ZmRu2rBjfoeYMShQP-TajF6Z4-swl2JRgkw&oe=66FB644A&_nc_sid=8f1549",
                        "width": 320
                    },
                    {
                        "height": 240,
                        "url": "https://instagram.fmnl4-7.fna.fbcdn.net/v/t51.29350-15/312985508_516547690048840_7681537962679898969_n.jpg?stp=c0.1.1280.1280a_dst-jpg_e35_s240x240&efg=eyJ2ZW5jb2RlX3RhZyI6ImltYWdlX3VybGdlbi4xMjgweDEyODMuc2RyLmYyOTM1MC5kZWZhdWx0X2ltYWdlIn0&_nc_ht=instagram.fmnl4-7.fna.fbcdn.net&_nc_cat=104&_nc_ohc=ET194TXqk_YQ7kNvgEphgzG&edm=AEhyXUkBAAAA&ccb=7-5&ig_cache_key=Mjk1OTcwNTQ4NzEwNjkwNTgyNg%3D%3D.3-ccb7-5&oh=00_AYBLwHufyGYzpfh6MxZ9ZOgbTqCl5SJR1vJR-rdqMGW8dg&oe=66FB644A&_nc_sid=8f1549",
                        "width": 240
                    },
                    {
                        "height": 150,
                        "url": "https://instagram.fmnl4-7.fna.fbcdn.net/v/t51.29350-15/312985508_516547690048840_7681537962679898969_n.jpg?stp=c0.1.1280.1280a_dst-jpg_e35_s150x150&efg=eyJ2ZW5jb2RlX3RhZyI6ImltYWdlX3VybGdlbi4xMjgweDEyODMuc2RyLmYyOTM1MC5kZWZhdWx0X2ltYWdlIn0&_nc_ht=instagram.fmnl4-7.fna.fbcdn.net&_nc_cat=104&_nc_ohc=ET194TXqk_YQ7kNvgEphgzG&_nc_gid=edf72fe289b045f2944e4f632c4d0cc0&edm=AEhyXUkBAAAA&ccb=7-5&ig_cache_key=Mjk1OTcwNTQ4NzEwNjkwNTgyNg%3D%3D.3-ccb7-5&oh=00_AYAQEkJnQOyTi4ECRoZ9tdG5Y8vHxFLDpULKCXM_FTxUZA&oe=66FB644A&_nc_sid=8f1549",
                        "width": 150
                    }
                ]
            },
            "inventory_source": null,
            "invited_coauthor_producers": [],
            "is_dash_eligible": null,
            "is_paid_partnership": false,
            "is_seen": null,
            "like_and_view_counts_disabled": false,
            "like_count": 4355,
            "link": null,
            "location": null,
            "main_feed_carousel_starting_media_id": null,
            "media_cropping_info": null,
            "media_level_comment_controls": null,
            "media_overlay_info": null,
            "media_type": 1,
            "number_of_qualities": null,
            "open_carousel_submission_state": null,
            "organic_tracking_token": "eyJ2ZXJzaW9uIjo1LCJwYXlsb2FkIjp7ImlzX2FuYWx5dGljc190cmFja2VkIjp0cnVlLCJ1dWlkIjoiZWRmNzJmZTI4OWIwNDVmMjk0NGU0ZjYzMmM0ZDBjYzAyOTU5NzA1NDg3MTA2OTA1ODI2In0sInNpZ25hdHVyZSI6IiJ9",
            "original_height": 1283,
            "original_width": 1280,
            "owner": {
                "__typename": "XDTUserDict",
                "friendship_status": null,
                "id": "2027519714",
                "is_embeds_disabled": null,
                "is_private": false,
                "is_unpublished": false,
                "is_verified": false,
                "pk": "2027519714",
                "profile_pic_url": "https://instagram.fmnl4-2.fna.fbcdn.net/v/t51.2885-19/11374159_753097248149705_168906061_a.jpg?stp=dst-jpg_s150x150&_nc_ht=instagram.fmnl4-2.fna.fbcdn.net&_nc_cat=105&_nc_ohc=3rj5kw39Jy8Q7kNvgE4yGuo&_nc_gid=edf72fe289b045f2944e4f632c4d0cc0&edm=AEhyXUkBAAAA&ccb=7-5&oh=00_AYCBiiL7cm_OH596-MrDlSr5uYfcsFwAwX-o8xIDxVWCTg&oe=66FB55A0&_nc_sid=8f1549",
                "show_account_transparency_details": true,
                "supervision_info": null,
                "transparency_label": null,
                "transparency_product": null,
                "transparency_product_enabled": false,
                "username": "yuihorie_official"
            },
            "photo_of_you": false,
            "pk": "2959705487106905826",
            "preview": null,
            "previous_submitter": null,
            "product_type": "feed",
            "saved_collection_ids": null,
            "share_urls": null,
            "sharing_friction_info": {
                "bloks_app_url": null,
                "should_have_sharing_friction": false
            },
            "social_context": null,
            "sponsor_tags": null,
            "story_cta": null,
            "taken_at": 1667044410,
            "thumbnails": null,
            "timeline_pinned_user_ids": null,
            "title": null,
            "top_likers": null,
            "upcoming_event": null,
            "user": {
                "__typename": "XDTUserDict",
                "friendship_status": null,
                "full_name": "\u5800\u6c5f\u7531\u8863",
                "hd_profile_pic_url_info": {
                    "url": "https://instagram.fmnl4-2.fna.fbcdn.net/v/t51.2885-19/11374159_753097248149705_168906061_a.jpg?_nc_ht=instagram.fmnl4-2.fna.fbcdn.net&_nc_cat=105&_nc_ohc=3rj5kw39Jy8Q7kNvgE4yGuo&_nc_gid=edf72fe289b045f2944e4f632c4d0cc0&edm=AEhyXUkBAAAA&ccb=7-5&oh=00_AYDYrEF1tvonjIuW52lEacDZrCTFUCsLgQKbEgTTirLEfQ&oe=66FB55A0&_nc_sid=8f1549"
                },
                "id": "2027519714",
                "is_embeds_disabled": null,
                "is_private": false,
                "is_unpublished": false,
                "is_verified": false,
                "latest_besties_reel_media": null,
                "latest_reel_media": null,
                "live_broadcast_id": null,
                "live_broadcast_visibility": null,
                "pk": "2027519714",
                "profile_pic_url": "https://instagram.fmnl4-2.fna.fbcdn.net/v/t51.2885-19/11374159_753097248149705_168906061_a.jpg?stp=dst-jpg_s150x150&_nc_ht=instagram.fmnl4-2.fna.fbcdn.net&_nc_cat=105&_nc_ohc=3rj5kw39Jy8Q7kNvgE4yGuo&_nc_gid=edf72fe289b045f2944e4f632c4d0cc0&edm=AEhyXUkBAAAA&ccb=7-5&oh=00_AYCBiiL7cm_OH596-MrDlSr5uYfcsFwAwX-o8xIDxVWCTg&oe=66FB55A0&_nc_sid=8f1549",
                "seen": null,
                "supervision_info": null,
                "username": "yuihorie_official"
            },
            "usertags": null,
            "video_dash_manifest": null,
            "video_versions": null,
            "view_count": null
        },
        "is_video": false,
        "owner": {
            "full_name": "\u5800\u6c5f\u7531\u8863",
            "id": "2027519714",
            "iphone_struct": {
                "__typename": "XDTUserDict",
                "friendship_status": null,
                "full_name": "\u5800\u6c5f\u7531\u8863",
                "hd_profile_pic_url_info": {
                    "url": "https://instagram.fmnl4-2.fna.fbcdn.net/v/t51.2885-19/11374159_753097248149705_168906061_a.jpg?_nc_ht=instagram.fmnl4-2.fna.fbcdn.net&_nc_cat=105&_nc_ohc=3rj5kw39Jy8Q7kNvgE4yGuo&_nc_gid=edf72fe289b045f2944e4f632c4d0cc0&edm=AEhyXUkBAAAA&ccb=7-5&oh=00_AYDYrEF1tvonjIuW52lEacDZrCTFUCsLgQKbEgTTirLEfQ&oe=66FB55A0&_nc_sid=8f1549"
                },
                "id": "2027519714",
                "is_embeds_disabled": null,
                "is_private": false,
                "is_unpublished": false,
                "is_verified": false,
                "latest_besties_reel_media": null,
                "latest_reel_media": null,
                "live_broadcast_id": null,
                "live_broadcast_visibility": null,
                "pk": "2027519714",
                "profile_pic_url": "https://instagram.fmnl4-2.fna.fbcdn.net/v/t51.2885-19/11374159_753097248149705_168906061_a.jpg?stp=dst-jpg_s150x150&_nc_ht=instagram.fmnl4-2.fna.fbcdn.net&_nc_cat=105&_nc_ohc=3rj5kw39Jy8Q7kNvgE4yGuo&_nc_gid=edf72fe289b045f2944e4f632c4d0cc0&edm=AEhyXUkBAAAA&ccb=7-5&oh=00_AYCBiiL7cm_OH596-MrDlSr5uYfcsFwAwX-o8xIDxVWCTg&oe=66FB55A0&_nc_sid=8f1549",
                "seen": null,
                "supervision_info": null,
                "username": "yuihorie_official"
            },
            "is_private": false,
            "profile_pic_url_hd": "https://instagram.fmnl4-2.fna.fbcdn.net/v/t51.2885-19/11374159_753097248149705_168906061_a.jpg?stp=dst-jpg_s150x150&_nc_ht=instagram.fmnl4-2.fna.fbcdn.net&_nc_cat=105&_nc_ohc=3rj5kw39Jy8Q7kNvgE4yGuo&_nc_gid=edf72fe289b045f2944e4f632c4d0cc0&edm=AEhyXUkBAAAA&ccb=7-5&oh=00_AYCBiiL7cm_OH596-MrDlSr5uYfcsFwAwX-o8xIDxVWCTg&oe=66FB55A0&_nc_sid=8f1549",
            "username": "yuihorie_official"
        },
        "shortcode": "CkS_HWWyBbi",
        "title": null,
        "viewer_has_liked": false
    }
}